{
  "id": "d02fd86d-3bff-46c3-8671-38da7b0300a2",
  "prevId": "c2269c95-d05a-4603-a5f8-1cbb41dd49b4",
  "version": "5",
  "dialect": "pg",
  "tables": {
    "companies": {
      "name": "companies",
      "schema": "",
      "columns": {
        "id": {
          "name": "id",
          "type": "serial",
          "primaryKey": true,
          "notNull": true
        },
        "name": {
          "name": "name",
          "type": "text",
          "primaryKey": false,
          "notNull": true
        },
        "symbol": {
          "name": "symbol",
          "type": "text",
          "primaryKey": false,
          "notNull": true
        },
        "company_data": {
          "name": "company_data",
          "type": "jsonb",
          "primaryKey": false,
          "notNull": false
        },
        "industry_data": {
          "name": "industry_data",
          "type": "jsonb",
          "primaryKey": false,
          "notNull": false
        },
        "competitors": {
          "name": "competitors",
          "type": "jsonb",
          "primaryKey": false,
          "notNull": false
        },
        "updated_at": {
          "name": "updated_at",
          "type": "timestamp",
          "primaryKey": false,
          "notNull": true,
          "default": "now()"
        },
        "organization_id": {
          "name": "organization_id",
          "type": "integer",
          "primaryKey": false,
          "notNull": true
        }
      },
      "indexes": {},
      "foreignKeys": {
        "companies_organization_id_organizations_id_fk": {
          "name": "companies_organization_id_organizations_id_fk",
          "tableFrom": "companies",
          "tableTo": "organizations",
          "columnsFrom": [
            "organization_id"
          ],
          "columnsTo": [
            "id"
          ],
          "onDelete": "no action",
          "onUpdate": "no action"
        }
      },
      "compositePrimaryKeys": {},
      "uniqueConstraints": {}
    },
    "financial_statements": {
      "name": "financial_statements",
      "schema": "",
      "columns": {
        "id": {
          "name": "id",
          "type": "serial",
          "primaryKey": true,
          "notNull": true
        },
        "name": {
          "name": "name",
          "type": "text",
          "primaryKey": false,
          "notNull": true
        },
        "balance_sheets": {
          "name": "balance_sheets",
          "type": "jsonb",
          "primaryKey": false,
          "notNull": false
        },
        "cash_flow_statements": {
          "name": "cash_flow_statements",
          "type": "jsonb",
          "primaryKey": false,
          "notNull": false
        },
        "income_statements": {
          "name": "income_statements",
          "type": "jsonb",
          "primaryKey": false,
          "notNull": false
        },
        "updated_at": {
          "name": "updated_at",
          "type": "timestamp",
          "primaryKey": false,
          "notNull": true,
          "default": "now()"
        }
      },
      "indexes": {},
      "foreignKeys": {},
      "compositePrimaryKeys": {},
      "uniqueConstraints": {}
    },
    "organizations": {
      "name": "organizations",
      "schema": "",
      "columns": {
        "id": {
          "name": "id",
          "type": "serial",
          "primaryKey": true,
          "notNull": true
        },
        "name": {
          "name": "name",
          "type": "text",
          "primaryKey": false,
          "notNull": true
        },
        "symbol": {
          "name": "symbol",
          "type": "text",
          "primaryKey": false,
          "notNull": true
        },
        "updated_at": {
          "name": "updated_at",
          "type": "timestamp",
          "primaryKey": false,
          "notNull": true,
          "default": "now()"
        }
      },
      "indexes": {},
      "foreignKeys": {},
      "compositePrimaryKeys": {},
      "uniqueConstraints": {}
    },
    "stocks": {
      "name": "stocks",
      "schema": "",
      "columns": {
        "id": {
          "name": "id",
          "type": "serial",
          "primaryKey": true,
          "notNull": true
        },
        "name": {
          "name": "name",
          "type": "text",
          "primaryKey": false,
          "notNull": true
        },
        "data": {
          "name": "data",
          "type": "jsonb",
          "primaryKey": false,
          "notNull": false
        },
        "updated_at": {
          "name": "updated_at",
          "type": "timestamp",
          "primaryKey": false,
          "notNull": true,
          "default": "now()"
        }
      },
      "indexes": {},
      "foreignKeys": {},
      "compositePrimaryKeys": {},
      "uniqueConstraints": {}
    },
    "symbols": {
      "name": "symbols",
      "schema": "",
      "columns": {
        "id": {
          "name": "id",
          "type": "serial",
          "primaryKey": true,
          "notNull": true
        },
        "symbol": {
          "name": "symbol",
          "type": "text",
          "primaryKey": false,
          "notNull": true
        },
        "exchange": {
          "name": "exchange",
          "type": "text",
          "primaryKey": false,
          "notNull": false
        },
        "exchange_short_name": {
          "name": "exchange_short_name",
          "type": "text",
          "primaryKey": false,
          "notNull": false
        },
        "price": {
          "name": "price",
          "type": "text",
          "primaryKey": false,
          "notNull": false
        },
        "name": {
          "name": "name",
          "type": "text",
          "primaryKey": false,
          "notNull": false
        },
        "type": {
          "name": "type",
          "type": "text",
          "primaryKey": false,
          "notNull": false
        },
        "updated_at": {
          "name": "updated_at",
          "type": "timestamp",
          "primaryKey": false,
          "notNull": true,
          "default": "now()"
        }
      },
      "indexes": {},
      "foreignKeys": {},
      "compositePrimaryKeys": {},
      "uniqueConstraints": {}
    }
  },
  "enums": {},
  "schemas": {},
  "_meta": {
    "columns": {},
    "schemas": {},
    "tables": {}
  }
}